odoo/addons/otrs_somconnexio/CHANGELOG.md
odoo/addons/otrs_somconnexio/__init__.py
odoo/addons/otrs_somconnexio/__manifest__.py
odoo/addons/otrs_somconnexio/crons/activate_change_tariff_OTRS_tickets_cron.xml
odoo/addons/otrs_somconnexio/listeners/__init__.py
odoo/addons/otrs_somconnexio/listeners/crm_lead_listener.py
odoo/addons/otrs_somconnexio/models/__init__.py
odoo/addons/otrs_somconnexio/models/contract.py
odoo/addons/otrs_somconnexio/models/crm_lead.py
odoo/addons/otrs_somconnexio/models/crm_lead_line.py
odoo/addons/otrs_somconnexio/models/mobile_contract_otrs_view.py
odoo/addons/otrs_somconnexio/models/partner_otrs_view.py
odoo/addons/otrs_somconnexio/models/res_partner.py
odoo/addons/otrs_somconnexio/models/isp_info/__init__.py
odoo/addons/otrs_somconnexio/models/isp_info/broadband.py
odoo/addons/otrs_somconnexio/otrs_factories/__init__.py
odoo/addons/otrs_somconnexio/otrs_factories/adsl_data_from_crm_lead_line.py
odoo/addons/otrs_somconnexio/otrs_factories/base_data.py
odoo/addons/otrs_somconnexio/otrs_factories/base_data_from_crm_lead_line.py
odoo/addons/otrs_somconnexio/otrs_factories/broadband_data_from_crm_lead_line.py
odoo/addons/otrs_somconnexio/otrs_factories/customer_data_from_res_partner.py
odoo/addons/otrs_somconnexio/otrs_factories/fiber_data_from_crm_lead_line.py
odoo/addons/otrs_somconnexio/otrs_factories/mobile_data_from_crm_lead_line.py
odoo/addons/otrs_somconnexio/otrs_factories/router_4G_data_from_crm_lead_line.py
odoo/addons/otrs_somconnexio/otrs_factories/service_data_from_crm_lead_line.py
odoo/addons/otrs_somconnexio/otrs_factories/switchboard_data_from_crm_lead_line.py
odoo/addons/otrs_somconnexio/otrs_services/update_ticket_with_error.py
odoo/addons/otrs_somconnexio/security/ir.model.access.csv
odoo/addons/otrs_somconnexio/services/__init__.py
odoo/addons/otrs_somconnexio/services/fiber_contract_to_pack.py
odoo/addons/otrs_somconnexio/services/mobile_activation_date_service.py
odoo/addons/otrs_somconnexio/services/schemas.py
odoo_addon_otrs_somconnexio-16.0.1.0.9.dist-info/METADATA
odoo_addon_otrs_somconnexio-16.0.1.0.9.dist-info/WHEEL
odoo_addon_otrs_somconnexio-16.0.1.0.9.dist-info/top_level.txt
odoo_addon_otrs_somconnexio-16.0.1.0.9.dist-info/RECORD
